{
    "product": {
        "id": "92",
        "category_id": "24",
        "type": "3",
        "name": "KVM VPS 1",
        "description": "<ul><\/ul>",
        "visible": "-1",
        "domain_options": "1",
        "qty": "0",
        "autosetup": "2",
        "subdomain": "",
        "owndomain": "1",
        "tax": "1",
        "tax_group_id": "1",
        "upgrades": [],
        "sort_order": "2",
        "autohostname": "",
        "p_options": [
            "64"
        ],
        "reg_document": "",
        "reg_document_kb": "",
        "code": "",
        "contract_id": "0",
        "dbcItemType": "",
        "baseUnitOfMeasureCode": "",
        "dbcItemId": "",
        "baseUnitOfMeasureId": "",
        "revenue_group": "3",
        "line_group_id": "1",
        "codeName": null,
        "layout": "left",
        "rel": "Product",
        "paytype": "Regular",
        "m_setup": "0.00",
        "q_setup": "0.00",
        "s_setup": "0.00",
        "a_setup": "0.00",
        "b_setup": "0.00",
        "t_setup": "0.00",
        "p4_setup": "0.00",
        "p5_setup": "0.00",
        "d_setup": "0.00",
        "w_setup": "0.00",
        "h_setup": 0,
        "m": "1000.00",
        "q": "3000.00",
        "s": "6000.00",
        "a": "12000.00",
        "b": "0.00",
        "t": "0.00",
        "p4": "0.00",
        "p5": "0.00",
        "d": "0.00",
        "w": "0.00",
        "h": 0,
        "ptype": "Dedicated",
        "tlds": null,
        "periods": null,
        "category_name": "VPS Hosting",
        "module": "39",
        "modules": [
            {
                "product_id": "92",
                "main": 1,
                "modname": "Zabbix",
                "filename": "class.zabbix.php",
                "module": "39",
                "options": false,
                "default": false,
                "server": {
                    "62": "62"
                }
            },
            {
                "product_id": "92",
                "module": "124",
                "main": "0",
                "server": {
                    "112": "112"
                },
                "options": false,
                "modname": "Managed Services",
                "filename": "class.manage_service.php",
                "default": false
            }
        ],
        "main": "1",
        "modname": "Zabbix",
        "filename": "class.zabbix.php",
        "domain_op": [],
        "free_domain": "0",
        "emails": {
            "AfterModuleTerminate": "0",
            "after_accountinsert": "0",
            "ProductAccountCreated": "0",
            "SuspendAccount": "0",
            "UnsuspendAccount": "0"
        },
        "a_upgrade": "0.00",
        "m_upgrade": "0.00",
        "q_upgrade": "0.00",
        "s_upgrade": "0.00",
        "tags": [],
        "out_of_stock": false,
        "service_type": "Hosting",
        "block_cancellation_day": 0,
        "0": true,
        "config": {
            "1OverdueReminder": "1",
            "1ServiceReminder": "0",
            "2OverdueReminder": "7",
            "2ServiceReminder": "0",
            "3OverdueReminder": "15",
            "3ServiceReminder": "0",
            "4ServiceReminder": "0",
            "5ServiceReminder": "0",
            "AddLateFeeAfter": "0",
            "AdsjustDatesOnCreation": "on",
            "AdvancedDueDate": "off",
            "AutoCancelUnpaidInvoices": "off",
            "AutoCancelUnpaidOrdersPeriod": "30",
            "AutoProcessCancellations": "off",
            "AutoSuspensionPeriod": "30",
            "AutoTerminationPeriod": "90",
            "BillFullMonth": "0",
            "CancellationPostPaidProrata": "off",
            "CancellationTypeEndPeriod": "on",
            "CancellationTypeImmediate": "on",
            "CreditOnDowngradeOverride": "",
            "EnableAutoCancelUnpaidOrders": "off",
            "EnableAutoCreation": "2",
            "EnableAutoRenewService": "on",
            "EnableAutoSuspension": "off",
            "EnableAutoTermination": "off",
            "EnableAutoUnSuspension": "off",
            "EnableAutoUpgrades": "on",
            "EnableProRata": "off",
            "InitialDueDays": "0",
            "InvoiceExpectDays": "0",
            "InvoiceGeneration": "30",
            "InvoiceUnpaidReminder": "3",
            "LateFeeType": "0",
            "LateFeeValue": "0",
            "MoveDueDays": "0",
            "ProRataDay": "1",
            "ProRataMonth": "disabled",
            "ProRataNextMonth": "0",
            "RecurringBillingType": "PrePay",
            "RenewInvoice": "1",
            "ReturnToStockOnTerminate": "0",
            "SendPaymentReminderEmails": "on",
            "UpgradeProratePrecision": "seconds",
            "InvoiceCustomReminder": null
        }
    },
    "addons": {
        "10": {
            "id": "43",
            "name": "Free monitoring (Zibbix)",
            "parentmod": "class.zabbix.php"
        }
    },
    "tasks": [],
    "widgets": [
        {
            "id": "370",
            "widget": "zabbix_monitor",
            "name": "Notification",
            "location": "includes\/modules\/Hosting\/zabbix\/widgets\/zabbix_monitor\/",
            "ptype": "0",
            "config": {
                "smallimg": "includes\/modules\/Hosting\/zabbix\/widgets\/zabbix_monitor\/small.png",
                "bigimg": "includes\/modules\/Hosting\/zabbix\/widgets\/zabbix_monitor\/big.png"
            },
            "options": "3",
            "group": "sidemenu",
            "widget_id": "35",
            "override_defaults": "0",
            "target_id": "92",
            "sort_order": "0",
            "assigned": "1",
            "unique": true,
            "configurable": false
        },
        {
            "id": "371",
            "widget": "zabbix_bandwidth",
            "name": "Bandwidth",
            "location": "includes\/modules\/Hosting\/zabbix\/widgets\/zabbix_bandwidth\/",
            "ptype": "0",
            "config": {
                "smallimg": "includes\/modules\/Hosting\/zabbix\/widgets\/zabbix_bandwidth\/small.png",
                "bigimg": "includes\/modules\/Hosting\/zabbix\/widgets\/zabbix_bandwidth\/big.png"
            },
            "options": "3",
            "group": "sidemenu",
            "widget_id": "36",
            "override_defaults": "0",
            "target_id": "92",
            "sort_order": "0",
            "assigned": "1",
            "unique": true,
            "configurable": false
        },
        {
            "id": "565",
            "widget": "manage_service_monitor",
            "name": "Monitor",
            "location": "includes\/modules\/Hosting\/manage_service\/widgets\/manage_service_monitor\/",
            "ptype": "0",
            "config": {
                "smallimg": "includes\/modules\/Hosting\/manage_service\/widgets\/manage_service_monitor\/small.png",
                "bigimg": "includes\/modules\/Hosting\/manage_service\/widgets\/manage_service_monitor\/big.png"
            },
            "options": "3",
            "group": "sidemenu",
            "widget_id": "59",
            "override_defaults": "0",
            "target_id": "92",
            "sort_order": "0",
            "assigned": "1",
            "unique": true,
            "configurable": false
        },
        {
            "id": "566",
            "widget": "manage_service_notification",
            "name": "Notification",
            "location": "includes\/modules\/Hosting\/manage_service\/widgets\/manage_service_notification\/",
            "ptype": "0",
            "config": {
                "smallimg": "includes\/modules\/Hosting\/manage_service\/widgets\/manage_service_notification\/small.png",
                "bigimg": "includes\/modules\/Hosting\/manage_service\/widgets\/manage_service_notification\/big.png"
            },
            "options": "3",
            "group": "sidemenu",
            "widget_id": "58",
            "override_defaults": "0",
            "target_id": "92",
            "sort_order": "0",
            "assigned": "1",
            "unique": true,
            "configurable": false
        }
    ],
    "forms": [
        {
            "id": "802",
            "type": "select",
            "required": "0",
            "name": "CPU Cores",
            "key": "",
            "variable": "cpu",
            "description": "",
            "category": "server",
            "product_id": "92",
            "copy_of": "802",
            "options": "275",
            "config": {
                "conditionals": []
            },
            "sort_order": "1",
            "group_id": "0",
            "ftype": "select",
            "premade": true,
            "items": [
                {
                    "id": "2615",
                    "category_id": "802",
                    "name": "1 core",
                    "variable_id": "cpu_quad_1",
                    "copy_of": "2615",
                    "pricing": true,
                    "paytype": "Free"
                },
                {
                    "id": "2616",
                    "category_id": "802",
                    "name": "2 cores",
                    "variable_id": "cpu_six_1",
                    "sort_order": "1",
                    "copy_of": "2616",
                    "pricing": true,
                    "paytype": "Regular"
                },
                {
                    "id": "2617",
                    "category_id": "802",
                    "name": "3 cores",
                    "variable_id": "cpu_quad_2",
                    "sort_order": "2",
                    "copy_of": "2617",
                    "pricing": true,
                    "paytype": "Regular"
                },
                {
                    "id": "2618",
                    "category_id": "802",
                    "name": "4 cores",
                    "variable_id": "cpu_six_2",
                    "sort_order": "3",
                    "copy_of": "2618",
                    "pricing": true,
                    "paytype": "Regular"
                }
            ]
        },
        {
            "id": "803",
            "type": "select",
            "required": "0",
            "name": "RAM",
            "key": "cf_memory",
            "variable": "ram",
            "description": "",
            "category": "server",
            "product_id": "92",
            "copy_of": "803",
            "options": "275",
            "config": {
                "conditionals": []
            },
            "sort_order": "2",
            "group_id": "0",
            "ftype": "select",
            "premade": true,
            "items": [
                {
                    "id": "2619",
                    "category_id": "803",
                    "name": "1GB",
                    "variable_id": "ram_1",
                    "copy_of": "2619",
                    "pricing": true,
                    "paytype": "Free"
                },
                {
                    "id": "2620",
                    "category_id": "803",
                    "name": "2GB",
                    "variable_id": "ram_2",
                    "sort_order": "1",
                    "copy_of": "2620",
                    "pricing": true,
                    "paytype": "Regular"
                },
                {
                    "id": "2621",
                    "category_id": "803",
                    "name": "3GB",
                    "variable_id": "ram_3",
                    "sort_order": "2",
                    "copy_of": "2621",
                    "pricing": true,
                    "paytype": "Regular"
                },
                {
                    "id": "2622",
                    "category_id": "803",
                    "name": "4GB",
                    "variable_id": "ram_4",
                    "sort_order": "3",
                    "copy_of": "2622",
                    "pricing": true,
                    "paytype": "Regular"
                }
            ]
        },
        {
            "id": "804",
            "type": "select",
            "required": "0",
            "name": "Domestic Bandwidth",
            "key": "cf_bandwidth",
            "variable": "bandwidth_dom",
            "description": "",
            "category": "network",
            "product_id": "92",
            "copy_of": "804",
            "options": "51",
            "config": {
                "conditionals": []
            },
            "sort_order": "3",
            "group_id": "0",
            "ftype": "select",
            "premade": true,
            "items": [
                {
                    "id": "2623",
                    "category_id": "804",
                    "name": "unlimited domestic dedicated 10 Mbps (inter max 1 Mbps)",
                    "variable_id": "bandwidth_dom_10",
                    "copy_of": "2623",
                    "pricing": true,
                    "paytype": "Free"
                },
                {
                    "id": "2624",
                    "category_id": "804",
                    "name": "unlimited domestic dedicated 100 Mbps (inter max 1 Mbps)",
                    "variable_id": "bandwidth_dom_100",
                    "sort_order": "1",
                    "copy_of": "2624",
                    "pricing": true,
                    "paytype": "Regular"
                },
                {
                    "id": "2625",
                    "category_id": "804",
                    "name": "unlimited domestic dedicated 1000 Mbps (inter max 1 Mbps)",
                    "variable_id": "bandwidth_dom_1000",
                    "sort_order": "2",
                    "copy_of": "2625",
                    "pricing": true,
                    "paytype": "Regular"
                }
            ]
        },
        {
            "id": "805",
            "type": "select",
            "required": "0",
            "name": "Inbound Internation Bandwidth",
            "key": "cf_bandwidth",
            "variable": "bandwidth_inter",
            "description": "",
            "category": "network",
            "product_id": "92",
            "copy_of": "805",
            "options": "19",
            "config": {
                "conditionals": []
            },
            "sort_order": "4",
            "group_id": "0",
            "ftype": "select",
            "premade": true,
            "items": [
                {
                    "id": "2626",
                    "category_id": "805",
                    "name": "Unlimited inbound international shared bandwidth 1 Mbps",
                    "variable_id": "bandwidth_inter_shared_1",
                    "copy_of": "2626",
                    "pricing": true,
                    "paytype": "Free"
                },
                {
                    "id": "2627",
                    "category_id": "805",
                    "name": "Unlimited inbound international dedicated bandwidth 1 Mbps",
                    "variable_id": "bandwidth_inter_dedicated_1",
                    "sort_order": "1",
                    "copy_of": "2627",
                    "pricing": true,
                    "paytype": "Regular"
                },
                {
                    "id": "2628",
                    "category_id": "805",
                    "name": "Unlimited inbound international dedicated bandwidth 2 Mbps",
                    "variable_id": "bandwidth_inter_dedicated_2",
                    "sort_order": "2",
                    "copy_of": "2628",
                    "pricing": true,
                    "paytype": "Regular"
                },
                {
                    "id": "2629",
                    "category_id": "805",
                    "name": "Unlimited inbound international dedicated bandwidth 3 Mbps",
                    "variable_id": "bandwidth_inter_dedicated_3",
                    "sort_order": "3",
                    "copy_of": "2629",
                    "pricing": true,
                    "paytype": "Regular"
                }
            ]
        },
        {
            "id": "806",
            "type": "select",
            "required": "0",
            "name": "IP Address",
            "key": "",
            "variable": "ip",
            "description": "",
            "category": "network",
            "product_id": "92",
            "copy_of": "806",
            "options": "307",
            "config": {
                "conditionals": []
            },
            "sort_order": "5",
            "group_id": "0",
            "ftype": "select",
            "premade": true,
            "items": [
                {
                    "id": "2630",
                    "category_id": "806",
                    "name": "2 (free)",
                    "variable_id": "2",
                    "copy_of": "2630",
                    "pricing": true,
                    "paytype": "Free"
                },
                {
                    "id": "2631",
                    "category_id": "806",
                    "name": "3",
                    "variable_id": "3",
                    "sort_order": "1",
                    "copy_of": "2631",
                    "pricing": true,
                    "paytype": "Regular"
                },
                {
                    "id": "2632",
                    "category_id": "806",
                    "name": "4",
                    "variable_id": "4",
                    "sort_order": "2",
                    "copy_of": "2632",
                    "pricing": true,
                    "paytype": "Regular"
                },
                {
                    "id": "2633",
                    "category_id": "806",
                    "name": "5",
                    "variable_id": "5",
                    "sort_order": "3",
                    "copy_of": "2633",
                    "pricing": true,
                    "paytype": "Regular"
                },
                {
                    "id": "2634",
                    "category_id": "806",
                    "name": "6",
                    "variable_id": "6",
                    "sort_order": "4",
                    "copy_of": "2634",
                    "pricing": true,
                    "paytype": "Regular"
                }
            ]
        },
        {
            "id": "807",
            "type": "select",
            "required": "0",
            "name": "Operating System",
            "key": "cf_os",
            "variable": "os",
            "description": "",
            "category": "software",
            "product_id": "92",
            "copy_of": "807",
            "options": "3",
            "config": {
                "conditionals": {
                    "1": {
                        "val": "2637",
                        "action": "hide",
                        "target": "808",
                        "targetname": "MSSQL",
                        "targetval": ""
                    },
                    "2": {
                        "val": "2638",
                        "action": "hide",
                        "target": "808",
                        "targetname": "MSSQL",
                        "targetval": ""
                    },
                    "3": {
                        "val": "2639",
                        "action": "hide",
                        "target": "808",
                        "targetname": "MSSQL",
                        "targetval": ""
                    },
                    "4": {
                        "val": "2640",
                        "action": "hide",
                        "target": "808",
                        "targetname": "MSSQL",
                        "targetval": ""
                    },
                    "5": {
                        "val": "2641",
                        "action": "hide",
                        "target": "808",
                        "targetname": "MSSQL",
                        "targetval": ""
                    },
                    "6": {
                        "val": "2642",
                        "action": "hide",
                        "target": "808",
                        "targetname": "MSSQL",
                        "targetval": ""
                    },
                    "7": {
                        "val": "2643",
                        "action": "hide",
                        "target": "808",
                        "targetname": "MSSQL",
                        "targetval": ""
                    },
                    "8": {
                        "val": "2644",
                        "action": "hide",
                        "target": "808",
                        "targetname": "MSSQL",
                        "targetval": ""
                    },
                    "9": {
                        "val": "2645",
                        "action": "hide",
                        "target": "808",
                        "targetname": "MSSQL",
                        "targetval": ""
                    },
                    "10": {
                        "val": "2646",
                        "action": "hide",
                        "target": "808",
                        "targetname": "MSSQL",
                        "targetval": ""
                    },
                    "11": {
                        "val": "2647",
                        "action": "hide",
                        "target": "808",
                        "targetname": "MSSQL",
                        "targetval": ""
                    }
                }
            },
            "sort_order": "6",
            "group_id": "0",
            "ftype": "select",
            "premade": true,
            "items": [
                {
                    "id": "2635",
                    "category_id": "807",
                    "name": "Cent OS 6 - 32 Bit",
                    "variable_id": "Cent OS 6 - 32 Bit",
                    "copy_of": "2635",
                    "pricing": true,
                    "paytype": "Free"
                },
                {
                    "id": "2636",
                    "category_id": "807",
                    "name": "Cent OS 6 - 64 Bit",
                    "variable_id": "Cent OS 6 - 64 Bit",
                    "sort_order": "1",
                    "copy_of": "2636",
                    "pricing": true,
                    "paytype": "Free"
                },
                {
                    "id": "2637",
                    "category_id": "807",
                    "name": "Cent OS 5 - 32 Bit",
                    "variable_id": "Cent Os 5 - 32 Bit",
                    "sort_order": "2",
                    "copy_of": "2637",
                    "pricing": true,
                    "paytype": "Free"
                },
                {
                    "id": "2638",
                    "category_id": "807",
                    "name": "Cent OS 5 - 64 Bit",
                    "variable_id": "Cent Os 5 - 64 Bit",
                    "sort_order": "3",
                    "copy_of": "2638",
                    "pricing": true,
                    "paytype": "Free"
                },
                {
                    "id": "2639",
                    "category_id": "807",
                    "name": "Ubuntu 10.04 - 32 Bit",
                    "variable_id": "Ubuntu 10.04 - 32 Bit",
                    "sort_order": "4",
                    "copy_of": "2639",
                    "pricing": true,
                    "paytype": "Free"
                },
                {
                    "id": "2640",
                    "category_id": "807",
                    "name": "Ubuntu 10.04 - 64 Bit",
                    "variable_id": "Ubuntu 10.04 - 64 Bit",
                    "sort_order": "5",
                    "copy_of": "2640",
                    "pricing": true,
                    "paytype": "Free"
                },
                {
                    "id": "2641",
                    "category_id": "807",
                    "name": "Fedora Core 13 - 32 Bit",
                    "variable_id": "Fedora Core 13 - 32 Bit",
                    "sort_order": "6",
                    "copy_of": "2641",
                    "pricing": true,
                    "paytype": "Free"
                },
                {
                    "id": "2642",
                    "category_id": "807",
                    "name": "Fedora Core 13 - 64 Bit",
                    "variable_id": "Fedora Core 13 - 64 Bit",
                    "sort_order": "7",
                    "copy_of": "2642",
                    "pricing": true,
                    "paytype": "Free"
                },
                {
                    "id": "2643",
                    "category_id": "807",
                    "name": "FreeBSD 8 - 32 Bit",
                    "variable_id": "FreeBSD 8 - 32 Bit",
                    "sort_order": "8",
                    "copy_of": "2643",
                    "pricing": true,
                    "paytype": "Free"
                },
                {
                    "id": "2644",
                    "category_id": "807",
                    "name": "FreeBSD 8 - 64 Bit",
                    "variable_id": "FreeBSD 8 - 64 Bit",
                    "sort_order": "9",
                    "copy_of": "2644",
                    "pricing": true,
                    "paytype": "Free"
                },
                {
                    "id": "2645",
                    "category_id": "807",
                    "name": "Xen Server 5 - 64 Bit",
                    "variable_id": "Xen Server 5 - 64 Bit",
                    "sort_order": "10",
                    "copy_of": "2645",
                    "pricing": true,
                    "paytype": "Free"
                },
                {
                    "id": "2646",
                    "category_id": "807",
                    "name": "VMware ESXi 4 - 64 Bit",
                    "variable_id": "VMware ESXi 4 - 64 Bit",
                    "sort_order": "11",
                    "copy_of": "2646",
                    "pricing": true,
                    "paytype": "Free"
                },
                {
                    "id": "2647",
                    "category_id": "807",
                    "name": "VMware ESXi 3.5 - 32 Bit",
                    "variable_id": "VMware ESXi 3.5 - 32 Bit",
                    "sort_order": "12",
                    "copy_of": "2647",
                    "pricing": true,
                    "paytype": "Free"
                },
                {
                    "id": "2648",
                    "category_id": "807",
                    "name": "Windows 2008 - Standard Edition 32 Bit",
                    "variable_id": "Windows 2008 - Standard Edition 32 Bit",
                    "sort_order": "13",
                    "copy_of": "2648",
                    "pricing": true,
                    "paytype": "Regular"
                },
                {
                    "id": "2649",
                    "category_id": "807",
                    "name": "Windows 2008 - Standard Edition 64 Bit",
                    "variable_id": "Windows 2008 - Standard Edition 64 Bit",
                    "sort_order": "14",
                    "copy_of": "2649",
                    "pricing": true,
                    "paytype": "Regular"
                }
            ]
        },
        {
            "id": "808",
            "type": "qty",
            "required": "0",
            "name": "MSSQL",
            "key": "",
            "variable": "mssql",
            "description": "",
            "category": "software",
            "product_id": "92",
            "copy_of": "808",
            "options": "50",
            "config": {
                "conditionals": [],
                "minvalue": 0,
                "maxvalue": 99999
            },
            "sort_order": "7",
            "group_id": "0",
            "ftype": "qty",
            "premade": true,
            "items": [
                {
                    "id": "2650",
                    "category_id": "808",
                    "copy_of": "2650",
                    "pricing": true,
                    "paytype": "Resources",
                    "scheme": "tiered",
                    "prices": [
                        {
                            "id": "63",
                            "item_id": "2650",
                            "qty": "0",
                            "qty_max": "99999",
                            "m_setup": "0.00",
                            "q_setup": "0.00",
                            "s_setup": "0.00",
                            "a_setup": "0.00",
                            "b_setup": "0.00",
                            "t_setup": "0.00",
                            "p4_setup": "0.00",
                            "p5_setup": "0.00",
                            "d_setup": "0.00",
                            "w_setup": "0.00",
                            "h_setup": "0.00",
                            "m": "1000.00",
                            "q": "0.00",
                            "s": "0.00",
                            "a": "12000.00",
                            "b": "0.00",
                            "t": "0.00",
                            "p4": "0.00",
                            "p5": "0.00",
                            "d": "0.00",
                            "w": "0.00",
                            "h": "0.00"
                        }
                    ]
                }
            ]
        },
        {
            "id": "809",
            "type": "select",
            "required": "0",
            "name": "Control Panel",
            "key": "cf_cp",
            "variable": "cp",
            "description": "",
            "category": "software",
            "product_id": "92",
            "copy_of": "809",
            "options": "259",
            "config": {
                "conditionals": []
            },
            "sort_order": "8",
            "group_id": "0",
            "ftype": "select",
            "premade": true,
            "items": [
                {
                    "id": "2651",
                    "category_id": "809",
                    "name": "cPanel\/WHM for VPS - Unlimited Domains (Linux Only)",
                    "variable_id": "cp_cpanel",
                    "copy_of": "2651",
                    "pricing": true,
                    "paytype": "Regular"
                },
                {
                    "id": "2652",
                    "category_id": "809",
                    "name": "cPanel\/WHM+CloudLinux for VPS - Unlimited Domains (Linux Only)",
                    "variable_id": "cp_cpanel_cloudlinux",
                    "sort_order": "1",
                    "copy_of": "2652",
                    "pricing": true,
                    "paytype": "Regular"
                },
                {
                    "id": "2653",
                    "category_id": "809",
                    "name": "None",
                    "variable_id": "cp_none",
                    "sort_order": "2",
                    "copy_of": "2653",
                    "pricing": true,
                    "paytype": "Free"
                }
            ]
        },
        {
            "id": "810",
            "type": "checkbox",
            "required": "0",
            "name": "Software",
            "key": "",
            "variable": "software",
            "description": "",
            "category": "software",
            "product_id": "92",
            "copy_of": "810",
            "options": "2",
            "config": {
                "minvalue": "",
                "maxvalue": 99999
            },
            "sort_order": "9",
            "group_id": "0",
            "ftype": "checkbox",
            "premade": true,
            "items": [
                {
                    "id": "2654",
                    "category_id": "810",
                    "name": "Netway cPanel Skin (\u0e20\u0e32\u0e29\u0e32\u0e44\u0e17\u0e22)",
                    "variable_id": "software_rvskin",
                    "copy_of": "2654",
                    "pricing": true,
                    "paytype": "Regular"
                },
                {
                    "id": "2655",
                    "category_id": "810",
                    "name": "Netway Site Builder (support cPanel and DirectAdmin)",
                    "variable_id": "software_rvsitebuilder",
                    "sort_order": "1",
                    "copy_of": "2655",
                    "pricing": true,
                    "paytype": "Regular"
                }
            ]
        },
        {
            "id": "811",
            "type": "checkbox",
            "required": "0",
            "name": "Managed Services",
            "key": "",
            "variable": "managed",
            "description": "",
            "category": "management",
            "product_id": "92",
            "copy_of": "811",
            "options": "259",
            "config": {
                "minvalue": "",
                "maxvalue": 99999
            },
            "sort_order": "10",
            "group_id": "0",
            "ftype": "checkbox",
            "premade": true,
            "items": [
                {
                    "id": "2656",
                    "category_id": "811",
                    "name": "Free Monitoring",
                    "variable_id": "managed_free",
                    "copy_of": "2656",
                    "pricing": true,
                    "paytype": "Free"
                },
                {
                    "id": "2657",
                    "category_id": "811",
                    "name": "Netway 'worry free' server management services (CentOS) - We handle everything for you, updates, security, monitoring, and more",
                    "variable_id": "managed_paid",
                    "sort_order": "1",
                    "copy_of": "2657",
                    "pricing": true,
                    "paytype": "Regular"
                }
            ]
        },
        {
            "id": "814",
            "type": "textarea",
            "required": "0",
            "name": "Additional Note:",
            "key": "",
            "variable": "",
            "description": "",
            "category": "",
            "product_id": "92",
            "copy_of": "814",
            "options": "2",
            "config": [],
            "sort_order": "13",
            "group_id": "0",
            "ftype": "textarea",
            "premade": true,
            "items": [
                {
                    "id": "2678",
                    "category_id": "814",
                    "copy_of": "2678",
                    "pricing": true,
                    "paytype": "Free"
                }
            ]
        },
        {
            "id": "815",
            "type": "select",
            "required": "0",
            "name": "\u0e02\u0e2d\u0e07 Internal Netway \u0e40\u0e2d\u0e07",
            "key": "",
            "variable": "netway",
            "description": "",
            "category": "",
            "product_id": "92",
            "copy_of": "815",
            "options": "4",
            "config": {
                "conditionals": []
            },
            "sort_order": "14",
            "group_id": "0",
            "ftype": "select",
            "premade": true,
            "items": [
                {
                    "id": "2679",
                    "category_id": "815",
                    "name": "\u0e44\u0e21\u0e48\u0e43\u0e0a\u0e48",
                    "copy_of": "2679"
                },
                {
                    "id": "2680",
                    "category_id": "815",
                    "name": "\u0e43\u0e0a\u0e48",
                    "variable_id": "1",
                    "sort_order": "1",
                    "copy_of": "2680"
                }
            ]
        }
    ],
    "metrics": []
}